tisit_keycloak_adapter/__init__.py
tisit_keycloak_adapter/decorators/__init__.py
tisit_keycloak_adapter/decorators/require_permission.py
tisit_keycloak_adapter/decorators/strip_request.py
tisit_keycloak_adapter/dependencies/__init__.py
tisit_keycloak_adapter/dependencies/check_permission.py
tisit_keycloak_adapter/dependencies/get_auth.py
tisit_keycloak_adapter/dependencies/get_authorization_result.py
tisit_keycloak_adapter/dependencies/get_user.py
tisit_keycloak_adapter/dependency_factory.py
tisit_keycloak_adapter/exceptions.py
tisit_keycloak_adapter/fast_api_user.py
tisit_keycloak_adapter/keycloak_backend.py
tisit_keycloak_adapter/middleware.py
tisit_keycloak_adapter/schemas/__init__.py
tisit_keycloak_adapter/schemas/authorization_methods.py
tisit_keycloak_adapter/schemas/authorization_result.py
tisit_keycloak_adapter/schemas/exception_response.py
tisit_keycloak_adapter/schemas/keycloak_configuration.py
tisit_keycloak_adapter/schemas/match_strategy.py
tisit_keycloak_adapter/schemas/validation_strategy.py
tisit_keycloak_adapter/setup.py
tisit_keycloak_adapter/setup_keycloak.py
tisit_keycloak_adapter-1.3.0.dev9.dist-info/METADATA
tisit_keycloak_adapter-1.3.0.dev9.dist-info/WHEEL
tisit_keycloak_adapter-1.3.0.dev9.dist-info/licenses/LICENSE
tisit_keycloak_adapter-1.3.0.dev9.dist-info/RECORD
