Metadata-Version: 2.4
Name: tisit-keycloak-adapter
Version: 1.3.0.dev9
Summary: Middleware for FastAPI to authenticate a user against keycloak
License-File: LICENSE
Author: Daniel Herrmann
Author-email: daniel.herrmann1@gmail.com
Requires-Python: >=3.10,<4.0
Classifier: Programming Language :: Python :: 3
Classifier: Programming Language :: Python :: 3.10
Classifier: Programming Language :: Python :: 3.11
Classifier: Programming Language :: Python :: 3.12
Classifier: Programming Language :: Python :: 3.13
Classifier: Programming Language :: Python :: 3.14
Requires-Dist: cachetools (>=6.1.0,<7.0.0)
Requires-Dist: fastapi (>=0.73.0)
Requires-Dist: jwcrypto (>=1.5.6,<2.0.0)
Requires-Dist: python-keycloak (>=4.1,<6)
